lolicon/__init__.py
lolicon/__main__.py
lolicon/cli.py
lolicon/constants.py
lolicon/lolicon.py
lolicon/utils.py
lolicon/chemistry/__init__.py
lolicon/chemistry/chemistry.py
lolicon/compsci/__init__.py
lolicon/compsci/compsci.py
lolicon/compsci/cryptography.py
lolicon/data/__init__.py
lolicon/data/elements.db
lolicon/data/planets.db
lolicon/data/satellites.db
lolicon/mathematics/__init__.py
lolicon/mathematics/mathematics.py
lolicon/physics/__init__.py
lolicon/physics/astronomy.py
lolicon-0.0.5a0.dist-info/LICENSE
lolicon-0.0.5a0.dist-info/METADATA
lolicon-0.0.5a0.dist-info/WHEEL
lolicon-0.0.5a0.dist-info/entry_points.txt
lolicon-0.0.5a0.dist-info/top_level.txt
lolicon-0.0.5a0.dist-info/RECORD
