Metadata-Version: 2.1
Name: lolicon
Version: 0.0.5a0
Summary: A STEM project that provides useful utility methods for engineering sciences and educational purposes.
Home-page: https://hentaichan.pythonanywhere.com/projects/lolicon
Author: hentai-chan
Author-email: dev.hentai-chan@outlook.com
License: UNKNOWN
Project-URL: Documentation, https://hentaichan.pythonanywhere.com/projects/lolicon
Project-URL: Source Code, https://github.com/hentai-chan/lolicon
Project-URL: Bug Reports, https://github.com/hentai-chan/lolicon/issues
Project-URL: Changelog, https://github.com/hentai-chan/lolicon/blob/master/CHANGELOG.md
Keywords: math physics chemistry engineering computer science
Platform: UNKNOWN
Classifier: Development Status :: 3 - Alpha
Classifier: License :: OSI Approved :: GNU General Public License v3 (GPLv3)
Classifier: Intended Audience :: Developers
Classifier: Natural Language :: English
Classifier: Programming Language :: Python :: 3.8
Classifier: Programming Language :: Python :: 3.9
Classifier: Operating System :: OS Independent
Classifier: Topic :: Education
Classifier: Topic :: Software Development :: Libraries
Classifier: Topic :: Utilities
Requires-Python: >=3.7
Requires-Dist: pint (==0.16.1)
Requires-Dist: colorama (==0.4.4)
Requires-Dist: click (==7.1.2)
Requires-Dist: rich (==9.10.0)
